second/__init__.py
second/watzpoppin.py
lmbr_second-1.0.2.dist-info/LICENSE
lmbr_second-1.0.2.dist-info/METADATA
lmbr_second-1.0.2.dist-info/WHEEL
lmbr_second-1.0.2.dist-info/entry_points.txt
lmbr_second-1.0.2.dist-info/top_level.txt
lmbr_second-1.0.2.dist-info/RECORD
