Metadata-Version: 2.1
Name: lmbr-second
Version: 1.0.2
Summary: Read the latest - lmbr
Home-page: https://github.com/realpython/second
Author: Lmbr
Author-email: lmbr@lmbr.com
License: MIT
Platform: UNKNOWN
Classifier: License :: OSI Approved :: MIT License
Classifier: Programming Language :: Python
Classifier: Programming Language :: Python :: 2
Classifier: Programming Language :: Python :: 3
Requires-Dist: lmbr-reader
